category_members/__init__.py
category_members/retrieve.py
mw_category_members-0.1.0.dist-info/METADATA
mw_category_members-0.1.0.dist-info/RECORD
mw_category_members-0.1.0.dist-info/WHEEL
mw_category_members-0.1.0.dist-info/top_level.txt
