Metadata-Version: 2.1
Name: mw-category-members
Version: 0.1.0
Summary: Using MediaWiki's API, retrieve pages that belong to a given category
Home-page: https://github.com/jfilter/mw-category-members
Author: Johannes Filter
Author-email: hi@jfilter.de
License: MIT
Platform: UNKNOWN
Classifier: Programming Language :: Python :: 3.6
Classifier: Programming Language :: Python :: 3.7
Classifier: License :: OSI Approved :: MIT License
Requires-Dist: requests
